collective.recipe.template-2.2-py3.9-nspkg.pth
collective/recipe/template/README.rst
collective/recipe/template/__init__.py
collective/recipe/template/genshitemplate.py
collective/recipe/template/genshitemplate.rst
collective/recipe/template/tests.py
collective.recipe.template-2.2.dist-info/METADATA
collective.recipe.template-2.2.dist-info/WHEEL
collective.recipe.template-2.2.dist-info/entry_points.txt
collective.recipe.template-2.2.dist-info/namespace_packages.txt
collective.recipe.template-2.2.dist-info/top_level.txt
collective.recipe.template-2.2.dist-info/RECORD
