Metadata-Version: 2.1
Name: collective.recipe.template
Version: 2.2
Summary: Buildout recipe to generate a text file from a template
Home-page: https://github.com/collective/collective.recipe.template
Author: Wichert Akkerman
Author-email: wichert@wiggy.net
License: BSD
Keywords: template recipe
Platform: UNKNOWN
Classifier: Framework :: Buildout
Classifier: Programming Language :: Python
Classifier: Programming Language :: Python :: 2
Classifier: Programming Language :: Python :: 2.7
Classifier: Programming Language :: Python :: 3
Classifier: Programming Language :: Python :: 3.5
Classifier: Programming Language :: Python :: 3.6
Classifier: Programming Language :: Python :: 3.7
Classifier: Programming Language :: Python :: 3.8
Classifier: Programming Language :: Python :: 3.9
Classifier: Programming Language :: Python :: 3.10
Classifier: Topic :: Software Development :: Libraries :: Python Modules
Requires-Dist: setuptools
Requires-Dist: six
Requires-Dist: zc.buildout
Provides-Extra: genshi
Requires-Dist: Genshi (>=0.7.0) ; extra == 'genshi'
Provides-Extra: test
Requires-Dist: zope.testing ; extra == 'test'
Requires-Dist: zope.testrunner ; extra == 'test'
